keract/__init__.py
keract/keract.py
keract-4.5.2.dist-info/LICENSE
keract-4.5.2.dist-info/METADATA
keract-4.5.2.dist-info/WHEEL
keract-4.5.2.dist-info/top_level.txt
keract-4.5.2.dist-info/RECORD
