Metadata-Version: 2.2
Name: keract
Version: 4.5.2
Summary: Keract - Tensorflow Keras Activations and Gradients
Author: Philippe Remy
License: MIT
License-File: LICENSE
Dynamic: author
Dynamic: description
Dynamic: description-content-type
Dynamic: license
Dynamic: summary
